MANIFEST.in
README
ez_setup.py
setup.cfg
setup.py
django_ldapbackend/__init__.py
django_ldapbackend/forms.py
django_ldapbackend/views.py
django_ldapbackend.egg-info/PKG-INFO
django_ldapbackend.egg-info/SOURCES.txt
django_ldapbackend.egg-info/dependency_links.txt
django_ldapbackend.egg-info/requires.txt
django_ldapbackend.egg-info/top_level.txt