Metadata-Version: 1.0
Name: django-ldapbackend
Version: 0.0.1.1
Summary: LDAP Backend for Django (1.0 or higher)
Home-page: http://django-ldapbackend.googlecode.com
Author: Alexander 'Swixel' Stanley
Author-email: lexi@swixel.net
License: New BSD
Download-URL: http://django-ldapbackend.googlecode.com/files/django-ldapbackend-0.0.1.tar.gz
Platform: Windows
Platform: POSIX
Classifier: Development Status :: 5 - Production/Stable
Classifier: Environment :: Web Environment
Classifier: Environment :: Plugins
Classifier: Framework :: Django
Classifier: Intended Audience :: Developers
Classifier: Intended Audience :: System Administrators
Classifier: License :: OSI Approved :: BSD License
Classifier: Operating System :: MacOS :: MacOS X
Classifier: Operating System :: Microsoft :: Windows
Classifier: Operating System :: POSIX
Classifier: Programming Language :: Python
Classifier: Topic :: Internet :: WWW/HTTP :: Site Management
Classifier: Topic :: Office/Business
Classifier: Topic :: System :: Systems Administration :: Authentication/Directory :: LDAP
